sls_data_analysis/__init__.py
sls_data_analysis/__main__.py
sls_data_analysis/mainwindow.py
sls_data_analysis/modules/__init__.py
sls_data_analysis/modules/fitter.py
sls_data_analysis/modules/h5_parser.py
sls_data_analysis/modules/istarmap.py
sls_data_analysis/resources/images/LOGO_CNRS_BLEU.png
sls_data_analysis/resources/images/Qt_logo_neon_2022.png
sls_data_analysis/widgets/data_plotter.py
sls_data_analysis/widgets/file_selector.py
sls_data_analysis/widgets/results.py
sls_data_analysis-0.1.2.dist-info/licenses/LICENSE
sls_data_analysis-0.1.2.dist-info/METADATA
sls_data_analysis-0.1.2.dist-info/WHEEL
sls_data_analysis-0.1.2.dist-info/entry_points.txt
sls_data_analysis-0.1.2.dist-info/top_level.txt
sls_data_analysis-0.1.2.dist-info/RECORD
