Metadata-Version: 2.4
Name: sls-data-analysis
Version: 0.1.2
Summary: A data analysis app for the SLS experiment
Author-email: Bastien Bégon <bastien.begon@crpp.cnrs.fr>
License: Copyright (c) 2025 Bastien Bégon
Project-URL: Homepage, https://src.koda.cnrs.fr/65sw9tz8/sls-data-analysis
Keywords: scattering,data,analysis,Mie
Classifier: License :: OSI Approved :: MIT License
Classifier: Programming Language :: Python
Classifier: Programming Language :: Python :: 3
Requires-Python: >=3.9
License-File: LICENSE
Requires-Dist: qtpy
Requires-Dist: numpy
Requires-Dist: scipy
Requires-Dist: pyqtgraph
Requires-Dist: matplotlib
Requires-Dist: h5py
Provides-Extra: pyqt6
Requires-Dist: PyQt6; extra == "pyqt6"
Provides-Extra: pyside6
Requires-Dist: PySide6<6.9.1; extra == "pyside6"
Dynamic: license-file
